{
  "version": 3,
  "configurePresets": [
    {
      "name": "locations-base",
      "hidden": true,
      "binaryDir": "${sourceDir}/build/${presetName}",
      "installDir": "${sourceDir}/out/install/${presetName}"
    },
    {
      "name": "warnings-base",
      "hidden": true,
      "warnings": {
        "dev": true,
        "deprecated": true,
        "systemVars": true
      },
      "errors": {
        "dev": true,
        "deprecated": false
      }
    },
    {
      "name": "ninja",
      "hidden": true,
      "displayName": "Ninja",
      "generator": "Ninja Multi-Config",
      "cacheVariables": {
        "CMAKE_DEFAULT_BUILD_TYPE": "Debug"
      }
    },
    {
      "name": "x64",
      "hidden": true,
      "architecture": {
        "value": "x64",
        "strategy": "external"
      }
    },
    {
      "name": "linux-x64-shared",
      "inherits": [ "ninja", "x64", "locations-base", "warnings-base" ],
      "condition": {"type": "equals", "lhs": "${hostSystemName}", "rhs": "Linux"},
      "cacheVariables": {
        "BUILD_SHARED_LIBS": "ON"
      }
    },
    {
      "name": "linux-x64-static",
      "inherits": [ "ninja", "x64", "locations-base", "warnings-base" ],
      "condition": {"type": "equals", "lhs": "${hostSystemName}", "rhs": "Linux"},
      "cacheVariables": {
        "BUILD_SHARED_LIBS": "OFF"
      }
    },
    {
      "name": "macos-x64-shared",
      "inherits": [ "ninja", "x64", "locations-base", "warnings-base" ],
      "condition": {"type": "equals", "lhs": "${hostSystemName}", "rhs": "Darwin"},
      "cacheVariables": {
        "BUILD_SHARED_LIBS": "ON"
      }
    },
    {
      "name": "macos-x64-static",
      "inherits": [ "ninja", "x64", "locations-base", "warnings-base" ],
      "condition": {"type": "equals", "lhs": "${hostSystemName}", "rhs": "Darwin"},
      "cacheVariables": {
        "BUILD_SHARED_LIBS": "OFF"
      }
    },
    {
      "name": "windows-x64-shared",
      "inherits": [ "ninja", "x64", "locations-base", "warnings-base" ],
      "condition": {"type": "equals", "lhs": "${hostSystemName}", "rhs": "Windows"},
      "cacheVariables": {
        "BUILD_SHARED_LIBS": "ON"
      }
    },
    {
      "name": "windows-x64-static",
      "inherits": [ "ninja", "x64", "locations-base", "warnings-base" ],
      "condition": {"type": "equals", "lhs": "${hostSystemName}", "rhs": "Windows"},
      "cacheVariables": {
        "BUILD_SHARED_LIBS": "OFF"
      }
    }
  ],
  "buildPresets": [
    {
      "name": "build-linux-x64-shared",
      "configurePreset": "linux-x64-shared",
      "nativeToolOptions": [ "-v" ],
      "condition": {"type": "equals", "lhs": "${hostSystemName}", "rhs": "Linux"}
    },
    {
      "name": "build-macos-x64-shared",
      "configurePreset": "macos-x64-shared",
      "nativeToolOptions": [ "-v" ],
      "condition": {"type": "equals", "lhs": "${hostSystemName}", "rhs": "Darwin"}
    },
    {
      "name": "build-windows-x64-shared",
      "configurePreset": "windows-x64-shared",
      "nativeToolOptions": [ "-v" ],
      "condition": {"type": "equals", "lhs": "${hostSystemName}", "rhs": "Windows"}
    },
    {
      "name": "install-linux-x64-shared",
      "inherits": "build-linux-x64-shared",
      "targets": [ "install" ],
      "condition": {"type": "equals", "lhs": "${hostSystemName}", "rhs": "Linux"}
    },
    {
      "name": "install-macos-x64-shared",
      "inherits": "build-macos-x64-shared",
      "targets": [ "install" ],
      "condition": {"type": "equals", "lhs": "${hostSystemName}", "rhs": "Darwin"}
    },
    {
      "name": "install-windows-x64-shared",
      "inherits": "build-windows-x64-shared",
      "targets": [ "install" ],
      "condition": {"type": "equals", "lhs": "${hostSystemName}", "rhs": "Windows"}
    },
    {
      "name": "build-linux-x64-static",
      "configurePreset": "linux-x64-static",
      "nativeToolOptions": [ "-v" ],
      "condition": {"type": "equals", "lhs": "${hostSystemName}", "rhs": "Linux"}
    },
    {
      "name": "build-macos-x64-static",
      "configurePreset": "macos-x64-static",
      "nativeToolOptions": [ "-v" ],
      "condition": {"type": "equals", "lhs": "${hostSystemName}", "rhs": "Darwin"}
    },
    {
      "name": "build-windows-x64-static",
      "configurePreset": "windows-x64-static",
      "nativeToolOptions": [ "-v" ],
      "condition": {"type": "equals", "lhs": "${hostSystemName}", "rhs": "Windows"}
    },
    {
      "name": "install-linux-x64-static",
      "inherits": "build-linux-x64-static",
      "targets": [ "install" ],
      "condition": {"type": "equals", "lhs": "${hostSystemName}", "rhs": "Linux"}
    },
    {
      "name": "install-macos-x64-static",
      "inherits": "build-macos-x64-static",
      "targets": [ "install" ],
      "condition": {"type": "equals", "lhs": "${hostSystemName}", "rhs": "Darwin"}
    },
    {
      "name": "install-windows-x64-static",
      "inherits": "build-windows-x64-static",
      "targets": [ "install" ],
      "condition": {"type": "equals", "lhs": "${hostSystemName}", "rhs": "Windows"}
    }
  ]
}
